git_history_tools-0.0.8.data/scripts/githistory
src/__init__.py
src/commit.py
src/gitutils.py
src/summary.py
git_history_tools-0.0.8.dist-info/LICENSE
git_history_tools-0.0.8.dist-info/METADATA
git_history_tools-0.0.8.dist-info/WHEEL
git_history_tools-0.0.8.dist-info/top_level.txt
git_history_tools-0.0.8.dist-info/RECORD
