Metadata-Version: 2.1
Name: git-history-tools
Version: 0.0.8
Summary: UNKNOWN
Home-page: https://github.com/orltom/git-history-tools
Author: Orlando Tomás
Author-email: orlando.tomas@hotmail.com
License: UNKNOWN
Platform: UNKNOWN
Classifier: Development Status :: 3 - Alpha
Classifier: Programming Language :: Python :: 3
Classifier: License :: OSI Approved :: MIT License
Requires-Python: >=3.6
Requires-Dist: tabulate
Requires-Dist: gitpython
Requires-Dist: docopt
